repo_gpt/__init__.py
repo_gpt/add_tests.py
repo_gpt/agents/__init__.py
repo_gpt/agents/autogen/__init__.py
repo_gpt/agents/autogen/repo_qna.py
repo_gpt/agents/autogen/user_proxy_function_call_agent.py
repo_gpt/agents/base_agent.py
repo_gpt/agents/central_intelligence.py
repo_gpt/agents/code_writer.py
repo_gpt/agents/repo_comprehender.py
repo_gpt/agents/simple_memory_store.py
repo_gpt/cli.py
repo_gpt/code_manager/__init__.py
repo_gpt/code_manager/abstract_extractor.py
repo_gpt/code_manager/code_dir_extractor.py
repo_gpt/code_manager/code_manager.py
repo_gpt/code_manager/code_processor.py
repo_gpt/code_manager/code_vscode_file_extractor.py
repo_gpt/codebase_analyzer/__init__.py
repo_gpt/codebase_analyzer/class_analyzer.py
repo_gpt/codebase_analyzer/dependency_analyzer.py
repo_gpt/codebase_analyzer/function_call_analyzer.py
repo_gpt/codebase_analyzer/graph_analyzer.py
repo_gpt/console.py
repo_gpt/file_handler/__init__.py
repo_gpt/file_handler/abstract_handler.py
repo_gpt/file_handler/generic_code_file_handler.py
repo_gpt/file_handler/generic_sql_file_handler.py
repo_gpt/logging_config.py
repo_gpt/openai_service.py
repo_gpt/prompt_service.py
repo_gpt/search_service.py
repo_gpt/test_generator.py
repo_gpt/utils.py
repo_gpt/vscode_prompt_service.py
repo_gpt-0.4.2.dist-info/LICENSE
repo_gpt-0.4.2.dist-info/METADATA
repo_gpt-0.4.2.dist-info/WHEEL
repo_gpt-0.4.2.dist-info/entry_points.txt
repo_gpt-0.4.2.dist-info/RECORD
