Metadata-Version: 2.3
Name: repo-gpt
Version: 0.4.2
Summary: Search your code repository using GPT4.
License: Apache-2.0
Keywords: openai,gpt,repo,repository,search,semantic-search,query,analyze-code,gpt3,gpt3.5
Author: Shruti Patel
Author-email: shruti222patel@gmail.com
Requires-Python: >=3.9,<3.13
Classifier: Intended Audience :: Developers
Classifier: License :: OSI Approved :: Apache Software License
Classifier: License :: OSI Approved :: MIT License
Classifier: Operating System :: OS Independent
Classifier: Programming Language :: Python :: 3
Classifier: Programming Language :: Python :: 3.9
Classifier: Programming Language :: Python :: 3.10
Classifier: Programming Language :: Python :: 3.11
Classifier: Programming Language :: Python :: 3.12
Classifier: Topic :: Software Development :: Libraries :: Python Modules
Requires-Dist: autogen (>=0.8.3,<0.9.0)
Requires-Dist: code2flow (>=2.5.1,<3.0.0)
Requires-Dist: colored (>=2.2.3,<3.0.0)
Requires-Dist: configargparse (>=1.7,<2.0)
Requires-Dist: fuzzywuzzy (>=0.18.0,<0.19.0)
Requires-Dist: multilspy (>=0.0.14,<0.0.15)
Requires-Dist: networkx (>=3.1,<4.0)
Requires-Dist: numpy (>=1.24.3,<2.0.0)
Requires-Dist: openai (>=1.68.2,<2.0.0)
Requires-Dist: pandas (>=2.0.2,<3.0.0)
Requires-Dist: pathspec (>=0.11.1,<0.12.0)
Requires-Dist: polars (>=0.19.12,<0.20.0)
Requires-Dist: pydeps (>=1.12.17,<2.0.0)
Requires-Dist: pylint (>=3.0.1,<4.0.0)
Requires-Dist: python-levenshtein (>=0.23.0,<0.24.0)
Requires-Dist: rich (>=13.4.1,<14.0.0)
Requires-Dist: tenacity (>=8.2.2,<9.0.0)
Requires-Dist: tiktoken (>=0.4.0,<0.5.0)
Requires-Dist: toml (>=0.10.2,<0.11.0)
Requires-Dist: tqdm (>=4.67.1,<5.0.0)
Requires-Dist: tree-sitter-languages (>=1.10.2,<2.0.0)
Requires-Dist: tree_sitter (>=0.20.4,<0.21.0)
Project-URL: Repository, https://github.com/shruti222patel/repo-gpt
